fraudcrawler/__init__.py
fraudcrawler/base/__init__.py
fraudcrawler/base/base.py
fraudcrawler/base/client.py
fraudcrawler/base/google-languages.json
fraudcrawler/base/google-locations.json
fraudcrawler/base/orchestrator.py
fraudcrawler/base/retry.py
fraudcrawler/cache/__init__.py
fraudcrawler/cache/redis_cacher.py
fraudcrawler/launch_demo_pipeline.py
fraudcrawler/processing/__init__.py
fraudcrawler/processing/base.py
fraudcrawler/processing/openai.py
fraudcrawler/scraping/__init__.py
fraudcrawler/scraping/enrich.py
fraudcrawler/scraping/search.py
fraudcrawler/scraping/url.py
fraudcrawler/scraping/zyte.py
fraudcrawler/settings.py
fraudcrawler-0.8.3.dist-info/LICENSE
fraudcrawler-0.8.3.dist-info/METADATA
fraudcrawler-0.8.3.dist-info/WHEEL
fraudcrawler-0.8.3.dist-info/entry_points.txt
fraudcrawler-0.8.3.dist-info/RECORD
