Metadata-Version: 2.1
Name: fraudcrawler
Version: 0.8.3
Summary: Intelligent Market Monitoring
Home-page: https://github.com/open-veanu/fraudcrawler
License: MIT
Author: Domingo Bertus
Author-email: hello@veanu.ch
Requires-Python: >=3.11,<4.0
Classifier: License :: OSI Approved :: MIT License
Classifier: Programming Language :: Python :: 3
Classifier: Programming Language :: Python :: 3.11
Classifier: Programming Language :: Python :: 3.12
Requires-Dist: aiocache[redis] (>=0.12.0,<0.13.0)
Requires-Dist: beautifulsoup4 (>=4.13.4,<5.0.0)
Requires-Dist: httpx (>=0.28.1,<0.29.0)
Requires-Dist: openai (>=1.68.2,<2.0.0)
Requires-Dist: pandas (>=2.2.3,<3.0.0)
Requires-Dist: pydantic-settings (>=2.8.1,<3.0.0)
Requires-Dist: requests (>=2.32.3,<3.0.0)
Requires-Dist: tenacity (>=9.1.2,<10.0.0)
Project-URL: Repository, https://github.com/open-veanu/fraudcrawler
